tb/__init__.py
tb/__main__.py
tb/checkfile.py
tb/crawler.py
tb/dyp.py
tb/exe.py
tb/getch.py
tb/make_class.py
tb/prt.py
tb/prt2.py
tb/setup.py
tb/sfz.py
tb/std.py
tb/str033.py
tb/tbsocket.py
tb/版权.py
tbutil-3.3.99.5.dist-info/METADATA
tbutil-3.3.99.5.dist-info/WHEEL
tbutil-3.3.99.5.dist-info/top_level.txt
tbutil-3.3.99.5.dist-info/RECORD
