Metadata-Version: 2.1
Name: tbutil
Version: 3.3.99.5
Summary: A tool for python
Home-page: https://gitee.com/laman29/toolbox
Author: laman29
Author-email: fzwxr@hotmail.com
License: UNKNOWN
Platform: UNKNOWN
Classifier: Programming Language :: Python :: 3
Classifier: License :: OSI Approved :: GNU General Public License v3 or later (GPLv3+)
Classifier: Operating System :: OS Independent
Requires-Python: >=3.6
